{
  "project_info": {
    "project_number": "23870320739",
    "project_id": "assignment-ed120",
    "storage_bucket": "assignment-ed120.appspot.com"
  },
  "client": [
    {
      "client_info": {
        "mobilesdk_app_id": "1:23870320739:android:d335cf9f72b2aeed650856",
        "android_client_info": {
          "package_name": "com.example.assignment"
        }
      },
      "oauth_client": [
        {
          "client_id": "23870320739-fut2pmsm9jabt4cr14dsgdkm8rm0di52.apps.googleusercontent.com",
          "client_type": 3
        }
      ],
      "api_key": [
        {
          "current_key": "AIzaSyD5us34aDgLFHD5WnjJexGSfoFIi8JIgV8"
        }
      ],
      "services": {
        "appinvite_service": {
          "other_platform_oauth_client": [
            {
              "client_id": "23870320739-fut2pmsm9jabt4cr14dsgdkm8rm0di52.apps.googleusercontent.com",
              "client_type": 3
            }
          ]
        }
      }
    }
  ],
  "configuration_version": "1"
}